vrobbler/__init__.py
vrobbler/apps/books/admin.py
vrobbler/apps/books/api/serializers.py
vrobbler/apps/books/api/views.py
vrobbler/apps/books/migrations/0001_initial.py
vrobbler/apps/books/migrations/__init__.py
vrobbler/apps/books/models.py
vrobbler/apps/books/utils.py
vrobbler/apps/music/__init__.py
vrobbler/apps/music/admin.py
vrobbler/apps/music/aggregators.py
vrobbler/apps/music/api/__init__.py
vrobbler/apps/music/api/serializers.py
vrobbler/apps/music/api/views.py
vrobbler/apps/music/apps.py
vrobbler/apps/music/constants.py
vrobbler/apps/music/context_processors.py
vrobbler/apps/music/migrations/0001_initial.py
vrobbler/apps/music/migrations/0002_alter_album_year.py
vrobbler/apps/music/migrations/0003_album_uuid_artist_uuid_track_uuid.py
vrobbler/apps/music/migrations/0004_alter_artist_options_alter_album_musicbrainz_id_and_more.py
vrobbler/apps/music/migrations/0005_album_cover_image.py
vrobbler/apps/music/migrations/0006_album_artists.py
vrobbler/apps/music/migrations/0007_alter_album_artists.py
vrobbler/apps/music/migrations/0008_alter_track_options.py
vrobbler/apps/music/migrations/0009_alter_track_musicbrainz_id_and_more.py
vrobbler/apps/music/migrations/0010_artist_biography_artist_theaudiodb_genre_and_more.py
vrobbler/apps/music/migrations/0011_artist_thumbnail.py
vrobbler/apps/music/migrations/0012_album_allmusic_id_album_discogs_id_and_more.py
vrobbler/apps/music/migrations/0013_alter_album_theaudiodb_score.py
vrobbler/apps/music/migrations/0014_album_theaudiodb_year_released.py
vrobbler/apps/music/migrations/__init__.py
vrobbler/apps/music/models.py
vrobbler/apps/music/serializers.py
vrobbler/apps/music/urls.py
vrobbler/apps/music/utils.py
vrobbler/apps/music/views.py
vrobbler/apps/podcasts/__init__.py
vrobbler/apps/podcasts/admin.py
vrobbler/apps/podcasts/apps.py
vrobbler/apps/podcasts/migrations/0001_initial.py
vrobbler/apps/podcasts/migrations/0002_episode_run_time_episode_run_time_ticks_and_more.py
vrobbler-0.11.12.dist-info/entry_points.txt
vrobbler-0.11.12.dist-info/WHEEL
vrobbler-0.11.12.dist-info/METADATA
vrobbler-0.11.12.dist-info/RECORD
